README.rst
setup.py
src/artifact_cli.egg-info/PKG-INFO
src/artifact_cli.egg-info/SOURCES.txt
src/artifact_cli.egg-info/dependency_links.txt
src/artifact_cli.egg-info/entry_points.txt
src/artifact_cli.egg-info/requires.txt
src/artifact_cli.egg-info/top_level.txt
src/artifactcli/__init__.py
src/artifactcli/argparser.py
src/artifactcli/artifactcli.py
src/artifactcli/repository.py
src/artifactcli/settings.py
src/artifactcli/artifact/__init__.py
src/artifactcli/artifact/artifact.py
src/artifactcli/artifact/baseinfo.py
src/artifactcli/artifact/basicinfo.py
src/artifactcli/artifact/fileinfo.py
src/artifactcli/artifact/gitinfo.py
src/artifactcli/driver/__init__.py
src/artifactcli/driver/basedriver.py
src/artifactcli/driver/mockdriver.py
src/artifactcli/driver/s3driver.py
src/artifactcli/operation/__init__.py
src/artifactcli/operation/baseoperation.py
src/artifactcli/operation/delete.py
src/artifactcli/operation/download.py
src/artifactcli/operation/help.py
src/artifactcli/operation/info.py
src/artifactcli/operation/list.py
src/artifactcli/operation/upload.py
src/artifactcli/util/__init__.py
src/artifactcli/util/asserttype.py
src/artifactcli/util/caseclass.py
src/artifactcli/util/progressbar.py
src/artifactcli/util/unicodeutil.py