Metadata-Version: 1.0
Name: artifact-cli
Version: 0.1.7
Summary: Private Artifact Manager using Amazon S3
Home-page: https://github.com/mogproject/artifact-cli
Author: mogproject
Author-email: mogproj@gmail.com
License: UNKNOWN
Platform: UNKNOWN
